sphinx_tabs/__init__.py
sphinx_tabs/tabs.py
sphinx_tabs/static/tabs.css
sphinx_tabs/static/tabs.js
sphinx_tabs-3.4.7.dist-info/LICENSE
sphinx_tabs-3.4.7.dist-info/METADATA
sphinx_tabs-3.4.7.dist-info/WHEEL
sphinx_tabs-3.4.7.dist-info/top_level.txt
sphinx_tabs-3.4.7.dist-info/RECORD
